{
    "entity":"orders",
    "description":"order entity",
    "attribute":[
            {
            "name":"order_id",
            "pk":1,
            "datatype":"int",
            "length":null,
            "scale":null,
            "link_entity":null,
            "description":"client id",
            "source":[
                    {
                    "source":"7a41e6d2-0d44-4345-86fc-3d273b1e7973",
                    "schema":"crm",
                    "table":"orders",
                    "column":"order_id"
                    }
                ]
        }
    ,
        {
            "name":"client_id",
            "pk":0,
            "datatype":"int",
            "length":null,
            "scale":null,
            "link_entity":"491458b0-b38a-46ba-99f9-492aebd54761",
            "description":"client id",
            "source":[
                    {
                    "source":"7a41e6d2-0d44-4345-86fc-3d273b1e7973",
                    "schema":"crm",
                    "table":"orders",
                    "column":"client_id"
                    }
                ]
        }
        ]

}